{"<PAD>": 0, "<UNK>": 1, "\u0e19": 2, "\u0e2d": 3, "\u0e48": 4, "\u0e32": 5, "\u0e49": 6, "\u0e21": 7, "\u0e40": 8, "\u0e01": 9, "\u0e07": 10, "\u0e22": 11, "\u0e23": 12, "\u0e44": 13, " ": 14, "\u0e31": 15, "\u0e27": 16, "\u0e35": 17, "\u0e14": 18, "\u0e30": 19, "\u0e25": 20, "\u0e1a": 21, "\u0e2b": 22, "\u0e04": 23, "\u0e41": 24, "\u0e1b": 25, "5": 26, "\u0e34": 27, "\u0e15": 28, "\u0e08": 29, "\u0e17": 30, "\u0e2a": 31, "e": 32, "a": 33, "\u0e37": 34, "\u0e1e": 35, "o": 36, "t": 37, "\u0e38": 38, "\u0e0a": 39, "\u0e43": 40, "\u0e47": 41, "\u0e39": 42, "d": 43, "\u0e46": 44, "i": 45, "\u0e02": 46, "l": 47, "n": 48, "s": 49, "\u0e42": 50, "r": 51, "c": 52, "\u0e33": 53, "\u0e36": 54, "u": 55, "2": 56, "\u0e1c": 57, "\u0e16": 58, "p": 59, "3": 60, "0": 61, "m": 62, "1": 63, "\u0e4c": 64, ".": 65, "h": 66, "/": 67, "\u0e1f": 68, "g": 69, "6": 70, "b": 71, "7": 72, "k": 73, "\u0e4b": 74, "8": 75, "\u0e0b": 76, "A": 77, "\n": 78, "f": 79, "4": 80, "w": 81, "y": 82, "9": 83, "\u0e13": 84, "v": 85, ":": 86, "Y": 87, "\u0e4a": 88, "-": 89, "_": 90, "\u0e1d": 91, "\u0e0d": 92, "\u0e2e": 93, "S": 94, "%": 95, "E": 96, "x": 97, "\u0e18": 98, "B": 99, "=": 100, "P": 101, "\u0e20": 102, "T": 103, "I": 104, "\u0e28": 105, "O": 106, "C": 107, "j": 108, "(": 109, ")": 110, "D": 111, "?": 112, "M": 113, "F": 114, "N": 115, "W": 116, "\u0e09": 117, "\u0e29": 118, "G": 119, "L": 120, "R": 121, "+": 122, "U": 123, ",": 124, "\ud83d\ude02": 125, "q": 126, "K": 127, "\ud83e\udd79": 128, "z": 129, "H": 130, "@": 131, "Q": 132, "Z": 133, "\ud83e\udd23": 134, "\ud83c\udffb": 135, "V": 136, "*": 137, "\ud83d\ude2d": 138, "J": 139, "!": 140, ";": 141, "\ud83d\udc80": 142, "\ufe0f": 143, "\u200d": 144, "X": 145, "\ud83e\udd72": 146, "'": 147, "&": 148, "\ud83d\ude05": 149}